LICENSE
README.md
setup.py
purifytext/__init__.py
purifytext/text_preprocessing.py
purifytext.egg-info/PKG-INFO
purifytext.egg-info/SOURCES.txt
purifytext.egg-info/dependency_links.txt
purifytext.egg-info/requires.txt
purifytext.egg-info/top_level.txt