Metadata-Version: 2.1
Name: purifytext
Version: 0.1.0
Summary: A package for cleaning and preprocessing text data
Author: Aman Kumar Jha
Author-email: vats.amankumarjha2002@gmail.com
Classifier: Programming Language :: Python :: 3
Classifier: License :: OSI Approved :: MIT License
Classifier: Operating System :: OS Independent
Requires-Python: >=3.6
License-File: LICENSE
Requires-Dist: numpy
Requires-Dist: pandas
Requires-Dist: beautifulsoup4
Requires-Dist: nltk
Requires-Dist: contractions
